llama_index/llms/llama_cpp/__init__.py
llama_index/llms/llama_cpp/base.py
llama_index/llms/llama_cpp/llama_utils.py
flying_delta_llms_llama_cpp-0.1.1.dist-info/METADATA
flying_delta_llms_llama_cpp-0.1.1.dist-info/WHEEL
flying_delta_llms_llama_cpp-0.1.1.dist-info/RECORD
